commonmark/__init__.py
commonmark/blocks.py
commonmark/cmark.py
commonmark/common.py
commonmark/dump.py
commonmark/entitytrans.py
commonmark/inlines.py
commonmark/main.py
commonmark/node.py
commonmark/normalize_reference.py
commonmark/render/__init__.py
commonmark/render/html.py
commonmark/render/renderer.py
commonmark/render/rst.py
commonmark/tests/__init__.py
commonmark/tests/rst_tests.py
commonmark/tests/run_spec_tests.py
commonmark/tests/unit_tests.py
commonmark_socialhome-0.9.1.post2.dist-info/LICENSE
commonmark_socialhome-0.9.1.post2.dist-info/METADATA
commonmark_socialhome-0.9.1.post2.dist-info/WHEEL
commonmark_socialhome-0.9.1.post2.dist-info/entry_points.txt
commonmark_socialhome-0.9.1.post2.dist-info/top_level.txt
commonmark_socialhome-0.9.1.post2.dist-info/RECORD
