Metadata-Version: 2.1
Name: commonmark_socialhome
Version: 0.9.1.post2
Summary: Python parser for the CommonMark Markdown spec, Socialhome fork
Author-email: Bibek Kafle <bkafle662@gmail.com>, Roland Shoemaker <rolandshoemaker@gmail.com>, Jason Robinson <mail@jasonrobinson.me>
Maintainer-email: Jason Robinson <mail@jasonrobinson.me>
License: Copyright (c) 2014, Bibek Kafle and Roland Shoemaker
Project-URL: Homepage, https://github.com/jaywink/commonmark.py
Project-URL: Issues, https://github.com/jaywink/commonmark.py/issues
Keywords: markup,markdown,commonmark
Classifier: Programming Language :: Python :: 3
Classifier: Development Status :: 5 - Production/Stable
Classifier: Environment :: Other Environment
Classifier: Environment :: Console
Classifier: Intended Audience :: Developers
Classifier: License :: OSI Approved :: BSD License
Classifier: Operating System :: OS Independent
Classifier: Topic :: Documentation
Classifier: Topic :: Internet :: WWW/HTTP :: Dynamic Content
Classifier: Topic :: Software Development :: Documentation
Classifier: Topic :: Software Development :: Libraries :: Python Modules
Classifier: Topic :: Text Processing :: Markup
Classifier: Topic :: Utilities
Requires-Python: >=3.8
License-File: LICENSE
